about_time/__init__.py
about_time/core.py
about_time/features.py
about_time/human_count.py
about_time/human_duration.py
about_time/human_throughput.py
about_time-4.2.0.data/data/LICENSE
about_time-4.2.0.dist-info/LICENSE
about_time-4.2.0.dist-info/METADATA
about_time-4.2.0.dist-info/WHEEL
about_time-4.2.0.dist-info/top_level.txt
about_time-4.2.0.dist-info/RECORD
