Metadata-Version: 2.1
Name: about-time
Version: 4.2.0
Summary: Easily measure timing and throughput of code blocks, with beautiful human friendly representations.
Home-page: https://github.com/rsalmei/about-time
Author: Rogério Sampaio de Almeida
Author-email: rsalmei@gmail.com
License: MIT
Keywords: python,track,tracker,time,code,blocks,monitor,statistics,analytics
Platform: UNKNOWN
Classifier: Development Status :: 5 - Production/Stable
Classifier: Intended Audience :: Developers
Classifier: Environment :: Console
Classifier: License :: OSI Approved :: MIT License
Classifier: Programming Language :: Python :: 3
Classifier: Programming Language :: Python :: 3.7
Classifier: Programming Language :: Python :: 3.8
Classifier: Programming Language :: Python :: 3.9
Classifier: Programming Language :: Python :: 3.10
Requires-Python: >=3.7, <4
